{
  "openapi": "3.0.1",
  "info": {
    "title": "backEnd",
    "version": "1.0"
  },
  "paths": {
    "/api/intentoPago": {
      "post": {
        "tags": [
          "intentoPago"
        ],
        "requestBody": {
          "content": {
            "application/json": {
              "schema": {
                "$ref": "#/components/schemas/createIntencionPagoRequest"
              }
            },
            "text/json": {
              "schema": {
                "$ref": "#/components/schemas/createIntencionPagoRequest"
              }
            },
            "application/*+json": {
              "schema": {
                "$ref": "#/components/schemas/createIntencionPagoRequest"
              }
            }
          }
        },
        "responses": {
          "200": {
            "description": "OK"
          }
        }
      },
      "get": {
        "tags": [
          "intentoPago"
        ],
        "responses": {
          "200": {
            "description": "OK"
          }
        }
      }
    },
    "/api/UsuarioDeudor": {
      "get": {
        "tags": [
          "UsuarioDeudor"
        ],
        "responses": {
          "200": {
            "description": "OK"
          }
        }
      }
    }
  },
  "components": {
    "schemas": {
      "createIntencionPagoRequest": {
        "type": "object",
        "properties": {
          "identificacion": {
            "type": "string",
            "nullable": true
          },
          "nombre": {
            "type": "string",
            "nullable": true
          },
          "montoPropuesto": {
            "type": "number",
            "format": "double"
          },
          "telefono": {
            "type": "string",
            "nullable": true
          },
          "fecha": {
            "type": "string",
            "format": "date-time"
          }
        },
        "additionalProperties": false
      }
    }
  }
}